{
  "stock_id": "2303",
  "name": "2303",
  "industry": "—",
  "generated_at": "2026-07-01 11:37",
  "quote": {
    "close": 169.0,
    "prev": 164.5,
    "change": 4.5,
    "change_pct": 2.74,
    "volume": 244699836
  },
  "ohlcv": {
    "date": [
      "2026-04-02",
      "2026-04-07",
      "2026-04-08",
      "2026-04-09",
      "2026-04-10",
      "2026-04-13",
      "2026-04-14",
      "2026-04-15",
      "2026-04-16",
      "2026-04-17",
      "2026-04-20",
      "2026-04-21",
      "2026-04-22",
      "2026-04-23",
      "2026-04-24",
      "2026-04-27",
      "2026-04-28",
      "2026-04-29",
      "2026-04-30",
      "2026-05-04",
      "2026-05-05",
      "2026-05-06",
      "2026-05-07",
      "2026-05-08",
      "2026-05-11",
      "2026-05-12",
      "2026-05-13",
      "2026-05-14",
      "2026-05-15",
      "2026-05-18",
      "2026-05-19",
      "2026-05-20",
      "2026-05-21",
      "2026-05-22",
      "2026-05-25",
      "2026-05-26",
      "2026-05-27",
      "2026-05-28",
      "2026-05-29",
      "2026-06-01",
      "2026-06-02",
      "2026-06-03",
      "2026-06-04",
      "2026-06-05",
      "2026-06-08",
      "2026-06-09",
      "2026-06-10",
      "2026-06-11",
      "2026-06-12",
      "2026-06-15",
      "2026-06-16",
      "2026-06-17",
      "2026-06-18",
      "2026-06-22",
      "2026-06-23",
      "2026-06-24",
      "2026-06-25",
      "2026-06-26",
      "2026-06-29",
      "2026-06-30",
      "2026-07-01"
    ],
    "open": [
      57.5,
      54.7,
      59.8,
      60.6,
      59.7,
      61.5,
      60.1,
      60.1,
      66.5,
      68.3,
      78.0,
      78.0,
      76.5,
      79.5,
      77.0,
      76.0,
      72.3,
      75.3,
      80.5,
      80.0,
      80.8,
      88.5,
      97.4,
      96.5,
      94.7,
      96.7,
      102.0,
      102.0,
      112.0,
      108.5,
      112.5,
      114.0,
      112.5,
      119.5,
      115.0,
      129.0,
      139.5,
      145.0,
      149.0,
      143.0,
      147.0,
      141.5,
      126.5,
      127.0,
      121.0,
      124.5,
      126.5,
      119.0,
      134.0,
      139.5,
      144.0,
      138.5,
      141.0,
      160.0,
      173.0,
      172.0,
      183.5,
      175.0,
      164.5,
      169.0,
      170.0
    ],
    "high": [
      57.8,
      58.9,
      61.7,
      60.6,
      63.5,
      61.5,
      60.4,
      63.4,
      68.3,
      74.8,
      80.2,
      78.5,
      79.8,
      79.5,
      78.3,
      76.4,
      77.7,
      75.3,
      80.9,
      82.4,
      85.2,
      91.4,
      98.8,
      98.8,
      96.3,
      104.5,
      102.0,
      108.0,
      118.0,
      114.0,
      120.5,
      115.5,
      118.0,
      119.5,
      125.0,
      133.5,
      143.5,
      151.0,
      149.0,
      155.5,
      150.0,
      141.5,
      131.5,
      133.0,
      125.0,
      131.5,
      130.5,
      126.0,
      137.5,
      143.5,
      144.5,
      142.0,
      146.0,
      160.0,
      176.0,
      185.5,
      185.5,
      176.0,
      167.0,
      173.5,
      173.0
    ],
    "low": [
      52.8,
      54.7,
      59.5,
      58.8,
      59.3,
      58.6,
      59.1,
      60.1,
      65.6,
      67.6,
      76.3,
      74.0,
      75.8,
      71.6,
      73.3,
      70.7,
      71.3,
      72.4,
      76.3,
      79.4,
      80.1,
      87.8,
      93.0,
      89.9,
      92.0,
      94.3,
      94.5,
      98.8,
      108.0,
      103.5,
      111.5,
      107.0,
      111.5,
      113.0,
      113.0,
      128.0,
      138.5,
      137.0,
      138.0,
      140.0,
      133.5,
      130.5,
      122.5,
      125.0,
      119.0,
      118.5,
      117.5,
      116.5,
      132.5,
      137.0,
      138.5,
      136.0,
      138.5,
      160.0,
      167.5,
      165.5,
      173.0,
      162.0,
      160.0,
      164.5,
      166.5
    ],
    "close": [
      53.6,
      58.3,
      60.3,
      60.0,
      62.0,
      60.1,
      59.7,
      62.1,
      68.3,
      73.0,
      76.9,
      76.2,
      78.6,
      73.6,
      74.5,
      72.7,
      75.1,
      74.5,
      77.3,
      81.2,
      83.1,
      91.4,
      96.5,
      91.3,
      95.0,
      104.5,
      98.4,
      108.0,
      110.0,
      111.0,
      113.0,
      108.0,
      116.0,
      114.0,
      125.0,
      130.5,
      143.5,
      142.0,
      144.5,
      146.0,
      141.5,
      130.5,
      125.0,
      131.5,
      121.0,
      127.5,
      118.5,
      125.0,
      133.5,
      141.5,
      141.0,
      140.0,
      145.5,
      160.0,
      170.0,
      178.0,
      178.5,
      164.0,
      164.0,
      164.5,
      169.0
    ],
    "volume": [
      113154703,
      164604452,
      161796136,
      76674808,
      151934929,
      123930917,
      73308726,
      144674939,
      282525368,
      497159388,
      350982291,
      317295735,
      232933889,
      231697954,
      180527350,
      186952751,
      163741430,
      120372117,
      333288108,
      242174345,
      173093862,
      256466477,
      325904228,
      219273944,
      178723421,
      383024476,
      352973233,
      333998329,
      413940731,
      264201488,
      273826419,
      227934594,
      198946094,
      203495119,
      340935766,
      291896012,
      280261963,
      418286433,
      366515715,
      289268747,
      380584577,
      379788969,
      380918568,
      377903061,
      318679993,
      374359529,
      346766316,
      362586174,
      393604121,
      328881762,
      256468191,
      171758079,
      307999583,
      66171376,
      550642760,
      566145556,
      397685486,
      382690528,
      222684902,
      300680863,
      244699836
    ]
  },
  "indicators": {
    "ma5": [
      56.46,
      56.56,
      57.220000000000006,
      57.92,
      58.839999999999996,
      60.14,
      60.419999999999995,
      60.779999999999994,
      62.44,
      64.64,
      68.0,
      71.3,
      74.6,
      75.66,
      75.96000000000001,
      75.11999999999999,
      74.9,
      74.08,
      74.82000000000001,
      76.16,
      78.24,
      81.5,
      85.9,
      88.7,
      91.46,
      95.74000000000001,
      97.14,
      99.44,
      103.17999999999999,
      106.38,
      108.08,
      110.0,
      111.6,
      112.4,
      115.2,
      118.7,
      125.8,
      131.0,
      137.1,
      141.3,
      143.5,
      140.9,
      137.5,
      134.9,
      129.9,
      127.1,
      124.7,
      124.7,
      125.1,
      129.2,
      131.9,
      136.2,
      140.3,
      145.6,
      151.3,
      158.7,
      166.4,
      170.1,
      170.9,
      169.8,
      168.0
    ],
    "ma20": [
      58.8,
      58.614999999999995,
      58.645,
      58.625,
      58.61500000000001,
      58.589999999999996,
      58.6,
      58.67999999999999,
      59.05999999999999,
      59.654999999999994,
      60.565,
      61.485,
      62.58,
      63.435,
      64.20500000000001,
      64.92999999999999,
      65.795,
      66.67,
      67.71000000000001,
      68.9,
      70.375,
      72.03,
      73.84,
      75.405,
      77.05499999999999,
      79.275,
      81.21000000000001,
      83.50500000000001,
      85.59,
      87.49000000000001,
      89.295,
      90.885,
      92.75500000000001,
      94.775,
      97.3,
      100.19000000000001,
      103.60999999999999,
      106.98499999999999,
      110.34499999999998,
      113.585,
      116.505,
      118.46,
      119.88499999999999,
      121.89499999999998,
      123.19499999999998,
      124.34499999999998,
      125.35,
      126.2,
      127.375,
      128.9,
      130.3,
      131.9,
      133.375,
      135.675,
      137.925,
      140.3,
      142.05,
      143.15,
      144.125,
      145.05,
      146.425
    ],
    "ma60": [
      59.98833333333334,
      60.1325,
      60.3125,
      60.49166666666667,
      60.71333333333334,
      60.906666666666666,
      61.08166666666666,
      61.215,
      61.473333333333336,
      61.77166666666666,
      62.13166666666667,
      62.486666666666665,
      62.89666666666667,
      63.21166666666667,
      63.47833333333334,
      63.64833333333333,
      63.769999999999996,
      63.87166666666666,
      64.03333333333333,
      64.30666666666666,
      64.53666666666668,
      64.78999999999999,
      65.13333333333334,
      65.515,
      66.05833333333334,
      66.78833333333334,
      67.415,
      68.185,
      68.99333333333333,
      69.81166666666667,
      70.65499999999999,
      71.41499999999999,
      72.30166666666666,
      73.13666666666667,
      74.095,
      75.17833333333333,
      76.47999999999999,
      77.77166666666666,
      79.13666666666667,
      80.57,
      81.89333333333333,
      83.035,
      84.12333333333332,
      85.30833333333334,
      86.28833333333333,
      87.40333333333334,
      88.38666666666667,
      89.46166666666666,
      90.675,
      92.015,
      93.38666666666667,
      94.75666666666666,
      96.23666666666666,
      97.96166666666666,
      99.80999999999999,
      101.80666666666666,
      103.81833333333333,
      105.60166666666666,
      107.39333333333333,
      109.17833333333333,
      111.10166666666666
    ],
    "bb_upper": [
      63.16203718703224,
      62.71135267807318,
      62.78338259786542,
      62.73141346906846,
      62.685574768674314,
      62.615131576796685,
      62.63563077962704,
      62.93186027398281,
      65.06785450801475,
      68.29431649343186,
      72.12213951132418,
      74.89611479333469,
      77.80029116534554,
      79.13096327588389,
      80.50488375806151,
      81.3943282663812,
      82.49816389821186,
      83.26639783364551,
      84.2297043429642,
      85.7187864885482,
      86.71144617669994,
      89.85453660724907,
      93.86528927447294,
      95.76558886543742,
      98.17595243067778,
      102.15287945638887,
      103.65918472321101,
      107.08469465451175,
      110.82513840909786,
      114.40044798078114,
      117.99772130872485,
      120.05277421456069,
      123.36634808496615,
      125.39607117656098,
      129.1840002773213,
      133.14559372693432,
      139.65429438752756,
      144.17511045680678,
      148.37581714388472,
      152.19785714424825,
      154.2336977190966,
      154.7354607500938,
      154.7395413487482,
      154.36357428020966,
      153.1111969860021,
      152.97597145253386,
      151.4451699503349,
      150.9904905367492,
      151.13891559088162,
      152.14831629444026,
      152.8794503685849,
      152.25112825011558,
      153.14173175339178,
      156.61922417555283,
      163.25082414100427,
      171.02698111466657,
      177.21113284804568,
      179.6553709098152,
      181.8049192646361,
      183.81637175371705,
      186.5868763977668
    ],
    "bb_lower": [
      54.437962812967754,
      54.51864732192681,
      54.50661740213459,
      54.51858653093154,
      54.544425231325704,
      54.56486842320331,
      54.56436922037296,
      54.42813972601718,
      53.05214549198523,
      51.015683506568124,
      49.00786048867581,
      48.07388520666532,
      47.35970883465446,
      47.73903672411612,
      47.905116241938515,
      48.465671733618784,
      49.09183610178815,
      50.07360216635449,
      51.190295657035826,
      52.081213511451814,
      54.03855382330006,
      54.20546339275093,
      53.814710725527064,
      55.04441113456258,
      55.9340475693222,
      56.39712054361114,
      58.760815276789,
      59.92530534548827,
      60.354861590902146,
      60.57955201921889,
      60.592278691275155,
      61.717225785439325,
      62.14365191503387,
      64.15392882343903,
      65.4159997226787,
      67.2344062730657,
      67.5657056124724,
      69.7948895431932,
      72.31418285611525,
      74.97214285575174,
      78.77630228090338,
      82.18453924990617,
      85.03045865125179,
      89.4264257197903,
      93.27880301399784,
      95.71402854746611,
      99.25483004966509,
      101.4095094632508,
      103.61108440911838,
      105.65168370555975,
      107.72054963141511,
      111.54887174988443,
      113.60826824660822,
      114.73077582444719,
      112.59917585899575,
      109.57301888533347,
      106.88886715195434,
      106.64462909018482,
      106.44508073536389,
      106.28362824628297,
      106.26312360223324
    ],
    "bb_mid": [
      58.8,
      58.614999999999995,
      58.645,
      58.625,
      58.61500000000001,
      58.589999999999996,
      58.6,
      58.67999999999999,
      59.05999999999999,
      59.654999999999994,
      60.565,
      61.485,
      62.58,
      63.435,
      64.20500000000001,
      64.92999999999999,
      65.795,
      66.67,
      67.71000000000001,
      68.9,
      70.375,
      72.03,
      73.84,
      75.405,
      77.05499999999999,
      79.275,
      81.21000000000001,
      83.50500000000001,
      85.59,
      87.49000000000001,
      89.295,
      90.885,
      92.75500000000001,
      94.775,
      97.3,
      100.19000000000001,
      103.60999999999999,
      106.98499999999999,
      110.34499999999998,
      113.585,
      116.505,
      118.46,
      119.88499999999999,
      121.89499999999998,
      123.19499999999998,
      124.34499999999998,
      125.35,
      126.2,
      127.375,
      128.9,
      130.3,
      131.9,
      133.375,
      135.675,
      137.925,
      140.3,
      142.05,
      143.15,
      144.125,
      145.05,
      146.425
    ],
    "kd_k": [
      25.840609183175403,
      44.59025686430152,
      57.816725546827605,
      65.51077582968661,
      72.33428668751752,
      70.96429081135985,
      68.80485430836808,
      74.84186548636016,
      83.22791032208957,
      85.83353225301752,
      85.46309557477832,
      84.13589087575528,
      86.95479144660547,
      81.11800911148012,
      78.40726673667417,
      73.1670335448029,
      70.46752007861133,
      65.23231497159375,
      65.0568374299283,
      73.28575486525864,
      77.36291703464327,
      84.90861135481855,
      87.21072310852892,
      82.57701825179142,
      83.77861822742238,
      89.18574548390984,
      85.58009509709395,
      90.38673006356379,
      86.55509356850699,
      83.31045972915012,
      80.70370517808821,
      73.51924571720969,
      77.08300591575137,
      76.45228384109646,
      84.30152255963807,
      86.65250399181105,
      91.10166932704071,
      87.75199007710748,
      86.9104176265169,
      84.74440212846548,
      79.22354081239986,
      66.54118407068873,
      53.77255408612006,
      44.93927848138032,
      31.786003005801682,
      29.298776778423427,
      20.40971083471534,
      20.871431154581213,
      30.829710321454677,
      51.417337744024195,
      63.4448918283078,
      70.27278502739654,
      79.6168849324078,
      86.41125662083891,
      87.57949320890708,
      88.09647373304371,
      87.66180009821284,
      77.29641892031317,
      70.38616480171339,
      66.1160290593404,
      65.70855837952557
    ],
    "kd_d": [
      29.673358725145814,
      34.64565810486438,
      42.36934725218546,
      50.08315677801918,
      57.5002000811853,
      61.98823032457682,
      64.26043831917391,
      67.78758070823599,
      72.93435724618719,
      77.23408224846398,
      79.97708669056877,
      81.36335475229761,
      83.22716698373357,
      82.52411435964909,
      81.15183181865746,
      78.49023239403928,
      75.8159949555633,
      72.28810162757345,
      69.8776802283584,
      71.01370510732515,
      73.13010908309786,
      77.05627650700475,
      80.44109204084614,
      81.15306744449458,
      82.02825103880386,
      84.41408252050586,
      84.80275337936857,
      86.66407894076698,
      86.627750483347,
      85.52198689861471,
      83.91589299177255,
      80.4503439002516,
      79.32789790541818,
      78.36935988397761,
      80.3467474425311,
      82.44866629229108,
      85.33300063720763,
      86.13933045050759,
      86.39635950917736,
      85.84570704894007,
      83.63831830342667,
      77.93927355918069,
      69.88370040149381,
      61.56889309478932,
      51.64126306512677,
      44.19376763622566,
      36.26574870238889,
      31.134309519786335,
      31.032776453675787,
      37.82763021712526,
      46.36671742085278,
      54.33540662303403,
      62.76256605949196,
      70.64546291327429,
      76.29013967848522,
      80.22558436333804,
      82.70432294162964,
      80.9016882678575,
      77.3965137791428,
      73.63635220587534,
      70.99375426375876
    ],
    "macd": [
      -1.503395811277251,
      -1.3247062694242473,
      -1.0100668133351505,
      -0.7759753099794651,
      -0.42418310296314843,
      -0.29529538404194255,
      -0.22285861982685162,
      0.027886521593252667,
      0.7186083671891481,
      1.6265117121182513,
      2.6304073617109296,
      3.331118684192816,
      4.033600561531131,
      4.139150743929733,
      4.246471818527738,
      4.138572696705339,
      4.198326117537306,
      4.149434055596103,
      4.287203134638233,
      4.657395967111256,
      5.045924300620186,
      5.954931692393629,
      7.0060921082572065,
      7.334994518312641,
      7.804248605754225,
      8.840795271348,
      9.065544992011525,
      9.904131867266301,
      10.607820936286217,
      11.118029512455266,
      11.550608544924401,
      11.359032475834127,
      11.717666239642782,
      11.70556829117784,
      12.440185929375644,
      13.312718997144586,
      14.881652665657057,
      15.821624597788968,
      16.57719662897165,
      17.099913216035347,
      16.95560383876574,
      15.771821804280833,
      14.225874947584344,
      13.371063308319748,
      11.711355462077464,
      10.796070335111807,
      9.237985744638877,
      8.430506527092973,
      8.379854644091552,
      8.882849839528149,
      9.135819296471055,
      9.150130759358277,
      9.49581488829432,
      10.815130774061359,
      12.52325426548498,
      14.356989146053508,
      15.669949646258999,
      15.363352321391403,
      14.948059803943664,
      14.49222595347672,
      14.328911957202337
    ],
    "macd_signal": [
      -1.093041911850863,
      -1.1393747833655399,
      -1.113513189359462,
      -1.0460056134834628,
      -0.9216411113793999,
      -0.7963719659119084,
      -0.6816692966948971,
      -0.5397581330372672,
      -0.2880848329919842,
      0.09483447603006295,
      0.6019490531662364,
      1.1477829793715524,
      1.7249464958034681,
      2.2077873454287213,
      2.615524240048525,
      2.9201339313798877,
      3.1757723686113715,
      3.370504706008318,
      3.5538443917343012,
      3.7745547068096927,
      4.0288286255717916,
      4.414049238936159,
      4.932457812800369,
      5.412965153902823,
      5.891221844273104,
      6.481136529688083,
      6.998018222152771,
      7.579240951175477,
      8.184956948197625,
      8.771571461049154,
      9.327378877824204,
      9.733709597426188,
      10.130500925869507,
      10.445514398931174,
      10.844448705020069,
      11.338102763444972,
      12.04681274388739,
      12.801775114667707,
      13.556859417528496,
      14.265470177229867,
      14.803496909537042,
      14.997161888485802,
      14.842904500305512,
      14.548536261908358,
      13.98110010194218,
      13.344094148576106,
      12.52287246778866,
      11.704399279649524,
      11.03949035253793,
      10.608162249935974,
      10.313693659242992,
      10.08098107926605,
      9.963947841071704,
      10.134184427669634,
      10.611998395232703,
      11.360996545396866,
      12.222787165569294,
      12.850900196733717,
      13.270332118175705,
      13.51471088523591,
      13.677551099629197
    ],
    "macd_hist": [
      -0.410353899426388,
      -0.18533148605870742,
      0.10344637602431161,
      0.2700303035039977,
      0.49745800841625143,
      0.5010765818699658,
      0.45881067686804544,
      0.5676446546305198,
      1.0066932001811324,
      1.5316772360881883,
      2.0284583085446934,
      2.183335704821264,
      2.3086540657276626,
      1.9313633985010115,
      1.630947578479213,
      1.218438765325451,
      1.0225537489259344,
      0.7789293495877851,
      0.7333587429039317,
      0.8828412603015634,
      1.0170956750483944,
      1.5408824534574697,
      2.073634295456838,
      1.922029364409818,
      1.9130267614811212,
      2.359658741659917,
      2.0675267698587536,
      2.3248909160908244,
      2.422863988088592,
      2.3464580514061115,
      2.223229667100197,
      1.625322878407939,
      1.5871653137732746,
      1.2600538922466669,
      1.5957372243555756,
      1.9746162336996136,
      2.8348399217696674,
      3.019849483121261,
      3.0203372114431524,
      2.83444303880548,
      2.1521069292286974,
      0.7746599157950307,
      -0.6170295527211671,
      -1.1774729535886106,
      -2.269744639864717,
      -2.548023813464299,
      -3.284886723149784,
      -3.2738927525565504,
      -2.6596357084463786,
      -1.7253124104078257,
      -1.1778743627719361,
      -0.9308503199077727,
      -0.46813295277738476,
      0.6809463463917247,
      1.9112558702522762,
      2.995992600656642,
      3.4471624806897054,
      2.5124521246576865,
      1.6777276857679588,
      0.9775150682408089,
      0.65136085757314
    ],
    "rsi14": [
      34.607806753465255,
      48.35439088438067,
      52.89250795174085,
      52.15223621215529,
      56.52110435398409,
      51.69228141664179,
      50.7100457076082,
      56.10005957036071,
      66.34024007455912,
      71.72469588859057,
      75.26110522856814,
      73.48458719505834,
      75.61029451745239,
      64.08381055826604,
      65.1147080198268,
      61.32358865471811,
      64.30751796312276,
      62.998937955860285,
      66.4318121877595,
      70.53267859812175,
      72.30761103248466,
      78.42209288126159,
      81.17289609650007,
      71.20550244665111,
      73.68183641441583,
      78.73789909902689,
      69.50451695233293,
      74.5605585707666,
      75.47291493513075,
      75.9375914441609,
      76.88097640493282,
      69.54068182328618,
      73.84372037010144,
      71.13800905552532,
      76.28485379709538,
      78.36252162932325,
      82.30794740455474,
      80.48434056930543,
      81.23073788893073,
      81.68339337895334,
      75.7789985164289,
      63.66453823378885,
      58.61856353587096,
      62.41040738422145,
      53.82962543508131,
      57.706258502181875,
      51.28532402547522,
      55.16543224664422,
      59.6872841114835,
      63.42607095935366,
      63.03259469901955,
      62.20147025608525,
      64.93966483132354,
      70.92055135404544,
      74.19053233754936,
      76.47010633264296,
      76.60916086446476,
      64.67285590015808,
      64.67285589940968,
      64.89161764870956,
      66.8794838430689
    ]
  },
  "chip": {
    "dates": [
      "2026-06-24",
      "2026-06-25",
      "2026-06-26",
      "2026-06-29",
      "2026-06-30",
      "2026-07-01"
    ],
    "foreign": [
      7332,
      11768,
      -16702,
      10372,
      35205,
      65873
    ],
    "trust": [
      -27265,
      -26376,
      -24162,
      -26114,
      -74093,
      -45793
    ],
    "dealer": [
      9435,
      3926,
      -2532,
      -1478,
      5133,
      5660
    ],
    "total": [
      -10498,
      -10682,
      -43396,
      -17220,
      -33755,
      25740
    ]
  },
  "signal": {
    "label": "出貨初期",
    "color": "#e74c3c",
    "desc": "主力開始調節，需留意短線風險"
  },
  "summary": [
    {
      "label": "趨勢方向",
      "value": "多頭趨勢",
      "direction": "up"
    },
    {
      "label": "價格位置",
      "value": "中軌以上",
      "direction": "up"
    },
    {
      "label": "均線排列",
      "value": "多頭排列（5>20>60）",
      "direction": "up"
    },
    {
      "label": "量價關係",
      "value": "量能平穩",
      "direction": "neutral"
    },
    {
      "label": "布林位置",
      "value": "中軌區間（78%）",
      "direction": "neutral"
    },
    {
      "label": "布林通道",
      "value": "開口擴大（趨勢加速）",
      "direction": "up"
    },
    {
      "label": "KD狀態",
      "value": "K 65.7 / D 71.0",
      "direction": "neutral"
    },
    {
      "label": "綜合評估",
      "value": "盤整觀望",
      "direction": "neutral"
    }
  ],
  "levels": {
    "resistance": "190 ～ 190",
    "pullback": "143 ～ 150",
    "support": "100 ～ 100",
    "breakdown": 146.0,
    "breakout": 178.0
  },
  "patterns": [
    {
      "label": "W底（未完成）",
      "desc": "右肩未完成，且頸線未突破",
      "date": ""
    },
    {
      "label": "M頭（未完成）",
      "desc": "右峰未確認，且尚未跌破頸線",
      "date": ""
    }
  ],
  "prediction": {
    "up": 0.33,
    "sideways": 0.34,
    "down": 0.33,
    "accuracy": 0.0,
    "error": "model not trained — run python model/train.py first"
  }
}