{
  "stock_id": "2317",
  "name": "2317",
  "industry": "—",
  "generated_at": "2026-07-22 10:37",
  "quote": {
    "close": 251.5,
    "prev": 246.0,
    "change": 5.5,
    "change_pct": 2.24,
    "volume": 67787081
  },
  "ohlcv": {
    "date": [
      "2026-04-24",
      "2026-04-27",
      "2026-04-28",
      "2026-04-29",
      "2026-04-30",
      "2026-05-04",
      "2026-05-05",
      "2026-05-06",
      "2026-05-07",
      "2026-05-08",
      "2026-05-11",
      "2026-05-12",
      "2026-05-13",
      "2026-05-14",
      "2026-05-15",
      "2026-05-18",
      "2026-05-19",
      "2026-05-20",
      "2026-05-21",
      "2026-05-22",
      "2026-05-25",
      "2026-05-26",
      "2026-05-27",
      "2026-05-28",
      "2026-05-29",
      "2026-06-01",
      "2026-06-02",
      "2026-06-03",
      "2026-06-04",
      "2026-06-05",
      "2026-06-08",
      "2026-06-09",
      "2026-06-10",
      "2026-06-11",
      "2026-06-12",
      "2026-06-15",
      "2026-06-16",
      "2026-06-17",
      "2026-06-18",
      "2026-06-22",
      "2026-06-23",
      "2026-06-24",
      "2026-06-25",
      "2026-06-26",
      "2026-06-29",
      "2026-06-30",
      "2026-07-01",
      "2026-07-02",
      "2026-07-03",
      "2026-07-06",
      "2026-07-07",
      "2026-07-08",
      "2026-07-09",
      "2026-07-13",
      "2026-07-14",
      "2026-07-15",
      "2026-07-16",
      "2026-07-17",
      "2026-07-20",
      "2026-07-21",
      "2026-07-22"
    ],
    "open": [
      227.0,
      224.0,
      230.0,
      226.0,
      224.5,
      224.0,
      227.5,
      246.5,
      255.0,
      254.0,
      256.5,
      254.0,
      246.5,
      255.0,
      249.0,
      251.0,
      251.0,
      246.5,
      245.0,
      249.0,
      255.0,
      262.5,
      263.0,
      265.0,
      269.0,
      302.0,
      297.5,
      306.0,
      309.0,
      290.5,
      257.5,
      270.5,
      271.0,
      260.0,
      266.5,
      271.0,
      270.0,
      266.0,
      270.5,
      270.0,
      270.0,
      255.0,
      260.5,
      255.5,
      250.0,
      251.5,
      255.0,
      239.0,
      237.0,
      243.5,
      243.0,
      240.0,
      238.0,
      242.0,
      236.0,
      236.0,
      240.5,
      238.0,
      235.5,
      238.0,
      249.0
    ],
    "high": [
      227.0,
      230.0,
      234.0,
      226.0,
      230.0,
      229.5,
      240.0,
      253.0,
      258.0,
      256.0,
      258.0,
      254.0,
      251.0,
      255.0,
      260.0,
      251.0,
      254.0,
      246.5,
      249.0,
      251.5,
      263.5,
      263.5,
      269.0,
      269.5,
      289.0,
      304.5,
      302.0,
      314.0,
      309.0,
      292.5,
      272.0,
      277.5,
      274.0,
      262.5,
      269.0,
      272.5,
      271.0,
      272.0,
      271.5,
      275.5,
      270.5,
      261.0,
      262.5,
      255.5,
      252.0,
      255.5,
      255.5,
      243.0,
      241.0,
      247.5,
      243.0,
      240.5,
      240.0,
      242.5,
      237.0,
      241.0,
      244.0,
      241.5,
      238.5,
      247.0,
      259.0
    ],
    "low": [
      218.0,
      220.0,
      225.0,
      222.0,
      219.5,
      223.5,
      227.0,
      245.0,
      250.0,
      245.5,
      251.0,
      246.0,
      242.5,
      244.0,
      247.0,
      241.0,
      244.0,
      239.5,
      244.0,
      245.0,
      255.0,
      257.0,
      261.0,
      259.5,
      268.0,
      293.0,
      293.0,
      299.0,
      293.0,
      278.0,
      257.5,
      268.5,
      262.5,
      251.5,
      260.0,
      265.0,
      265.5,
      264.0,
      268.5,
      268.5,
      259.0,
      255.0,
      257.5,
      248.0,
      246.0,
      249.0,
      248.0,
      238.0,
      236.0,
      240.5,
      236.0,
      234.0,
      234.5,
      236.5,
      230.0,
      235.5,
      238.0,
      233.0,
      230.5,
      236.5,
      248.0
    ],
    "close": [
      221.5,
      228.0,
      225.5,
      225.0,
      219.5,
      227.5,
      239.5,
      252.0,
      253.5,
      250.0,
      252.0,
      250.0,
      251.0,
      244.5,
      248.5,
      248.5,
      245.0,
      240.0,
      247.5,
      250.0,
      261.0,
      259.0,
      264.0,
      263.0,
      289.0,
      293.5,
      301.5,
      309.0,
      293.0,
      284.5,
      269.5,
      277.5,
      263.0,
      258.5,
      260.5,
      267.5,
      269.0,
      272.0,
      268.5,
      268.5,
      259.5,
      256.0,
      257.5,
      248.5,
      246.5,
      251.0,
      248.0,
      239.0,
      240.5,
      242.0,
      237.0,
      237.5,
      237.5,
      236.5,
      235.5,
      239.0,
      242.5,
      234.0,
      234.5,
      246.0,
      251.5
    ],
    "volume": [
      77230253,
      109457408,
      104089860,
      43603455,
      73683654,
      57506042,
      162873566,
      240330399,
      128767846,
      102375417,
      63063740,
      84325367,
      72415109,
      73360409,
      138413483,
      63512356,
      70223341,
      62650287,
      51483466,
      56310552,
      122990174,
      55665305,
      78352856,
      73792269,
      289511198,
      205766647,
      113076476,
      149620933,
      110760779,
      93158859,
      117863651,
      74649081,
      93369272,
      97550509,
      60260948,
      54689024,
      56878574,
      42755242,
      68996866,
      67145972,
      92063800,
      63690545,
      43578494,
      80450955,
      49210311,
      52952173,
      65880617,
      67897136,
      51008242,
      43693584,
      51778760,
      37939126,
      40528079,
      37504587,
      48112076,
      36108846,
      39074704,
      69006897,
      48579978,
      51471036,
      67787081
    ]
  },
  "indicators": {
    "ma5": [
      217.2,
      221.3,
      224.2,
      225.0,
      223.9,
      225.1,
      227.4,
      232.7,
      238.4,
      244.5,
      249.4,
      251.5,
      251.3,
      249.5,
      249.2,
      248.5,
      247.5,
      245.3,
      245.9,
      246.2,
      248.7,
      251.5,
      256.3,
      259.4,
      267.2,
      273.7,
      282.2,
      291.2,
      297.2,
      296.3,
      291.5,
      286.7,
      277.5,
      270.6,
      265.8,
      265.4,
      263.7,
      265.5,
      267.5,
      269.1,
      267.5,
      264.9,
      262.0,
      258.0,
      253.6,
      251.9,
      250.3,
      246.6,
      245.0,
      244.1,
      241.3,
      239.2,
      238.9,
      238.1,
      236.8,
      237.2,
      238.2,
      237.5,
      237.1,
      239.2,
      241.7
    ],
    "ma20": [
      203.975,
      205.35,
      206.65,
      208.2,
      209.8,
      211.325,
      213.65,
      216.65,
      219.25,
      221.75,
      224.325,
      226.825,
      229.0,
      230.85,
      232.925,
      235.05,
      236.925,
      238.375,
      239.7,
      240.95,
      242.925,
      244.475,
      246.4,
      248.3,
      251.775,
      255.075,
      258.175,
      261.025,
      263.0,
      264.725,
      265.6,
      266.975,
      267.575,
      268.275,
      268.875,
      269.825,
      271.025,
      272.625,
      273.675,
      274.6,
      274.525,
      274.375,
      274.05,
      273.325,
      271.2,
      269.075,
      266.4,
      262.9,
      260.275,
      258.15,
      256.525,
      254.525,
      253.25,
      252.15,
      250.9,
      249.475,
      248.15,
      246.25,
      244.55,
      243.425,
      243.025
    ],
    "ma60": [
      214.175,
      214.15,
      214.18333333333334,
      214.28333333333333,
      214.21666666666667,
      214.31666666666666,
      214.575,
      215.01666666666668,
      215.48333333333332,
      215.91666666666666,
      216.44166666666666,
      217.03333333333333,
      217.60833333333332,
      218.03333333333333,
      218.58333333333334,
      219.14166666666668,
      219.58333333333334,
      219.9,
      220.24166666666667,
      220.6,
      221.08333333333334,
      221.29166666666666,
      221.64166666666668,
      222.04166666666666,
      223.04166666666666,
      224.31666666666666,
      225.60833333333332,
      227.04166666666666,
      228.41666666666666,
      229.66666666666666,
      230.50833333333333,
      231.55833333333334,
      232.36666666666667,
      233.06666666666666,
      233.875,
      234.83333333333334,
      235.9,
      237.05,
      238.25833333333333,
      239.48333333333332,
      240.475,
      241.4,
      242.36666666666667,
      243.275,
      244.25833333333333,
      245.15833333333333,
      246.075,
      246.85833333333332,
      247.50833333333333,
      248.20833333333334,
      248.81666666666666,
      249.44166666666666,
      249.94166666666666,
      250.425,
      250.9,
      251.45,
      252.03333333333333,
      252.41666666666666,
      252.64166666666668,
      252.99166666666667,
      253.49166666666667
    ],
    "bb_upper": [
      223.99729021024217,
      227.97532349288946,
      230.79670076624836,
      232.90116127677106,
      232.9525831229079,
      234.94095134426595,
      238.77725507031005,
      245.01250304446646,
      251.08592806546517,
      255.04058662587272,
      258.64589282362164,
      260.9690832510206,
      263.50095345745797,
      264.4531013606278,
      265.4345532517993,
      265.6491055940838,
      264.8991892314663,
      263.5582755697317,
      263.7993557459201,
      264.4242860437362,
      266.15446178319314,
      267.64820367193624,
      269.33147687304364,
      270.0313743601028,
      276.1783539541292,
      283.21987893962773,
      292.15064917469704,
      301.7183008840778,
      305.9283368564768,
      308.2227010886781,
      308.72234736311617,
      309.7553139675001,
      309.74417682009215,
      309.2801023782726,
      309.0035762465968,
      308.8057982419413,
      308.22499292586224,
      306.8393014111442,
      305.87221302093997,
      304.94295201265203,
      305.0165432624574,
      305.21563450777404,
      305.4822998471987,
      306.4535772646358,
      305.5256847211959,
      302.84554929964855,
      297.74460416923944,
      289.48769006811006,
      284.62221425759515,
      280.965276507315,
      280.53481159092166,
      277.8318207771205,
      277.3801296700766,
      277.2583965825646,
      276.7367343545045,
      274.59047017487893,
      271.67400789339246,
      267.71110312561746,
      263.8697471924172,
      259.16056146874985,
      257.38677309094356
    ],
    "bb_lower": [
      183.95270978975782,
      182.72467650711053,
      182.50329923375165,
      183.4988387232289,
      186.64741687709213,
      187.70904865573402,
      188.52274492968996,
      188.28749695553356,
      187.41407193453483,
      188.45941337412728,
      190.00410717637834,
      192.68091674897934,
      194.49904654254203,
      197.24689863937218,
      200.41544674820074,
      204.45089440591624,
      208.95081076853367,
      213.19172443026832,
      215.6006442540799,
      217.4757139562638,
      219.69553821680688,
      221.30179632806374,
      223.46852312695637,
      226.5686256398972,
      227.37164604587085,
      226.93012106037227,
      224.19935082530301,
      220.33169911592213,
      220.0716631435232,
      221.22729891132195,
      222.47765263688387,
      224.19468603249993,
      225.40582317990783,
      227.26989762172735,
      228.74642375340315,
      230.84420175805863,
      233.82500707413772,
      238.41069858885578,
      241.47778697906006,
      244.25704798734802,
      244.03345673754254,
      243.53436549222596,
      242.6177001528013,
      240.1964227353642,
      236.8743152788041,
      235.30445070035145,
      235.0553958307605,
      236.31230993188987,
      235.9277857424048,
      235.3347234926849,
      232.5151884090783,
      231.21817922287946,
      229.1198703299234,
      227.04160341743543,
      225.06326564549548,
      224.35952982512106,
      224.62599210660758,
      224.78889687438254,
      225.23025280758284,
      227.68943853125018,
      228.66322690905642
    ],
    "bb_mid": [
      203.975,
      205.35,
      206.65,
      208.2,
      209.8,
      211.325,
      213.65,
      216.65,
      219.25,
      221.75,
      224.325,
      226.825,
      229.0,
      230.85,
      232.925,
      235.05,
      236.925,
      238.375,
      239.7,
      240.95,
      242.925,
      244.475,
      246.4,
      248.3,
      251.775,
      255.075,
      258.175,
      261.025,
      263.0,
      264.725,
      265.6,
      266.975,
      267.575,
      268.275,
      268.875,
      269.825,
      271.025,
      272.625,
      273.675,
      274.6,
      274.525,
      274.375,
      274.05,
      273.325,
      271.2,
      269.075,
      266.4,
      262.9,
      260.275,
      258.15,
      256.525,
      254.525,
      253.25,
      252.15,
      250.9,
      249.475,
      248.15,
      246.25,
      244.55,
      243.425,
      243.025
    ],
    "kd_k": [
      74.4236960388483,
      77.29941317750283,
      75.57665796454144,
      73.88170640182007,
      66.20362347634504,
      68.62554490159779,
      78.47763599381452,
      84.69937637590357,
      86.0495842498628,
      83.77331590614907,
      83.98740540856332,
      82.3985300119494,
      82.2050806133185,
      75.09324214742134,
      71.77933314812785,
      61.010783501568156,
      47.69139952699189,
      32.60727448136957,
      34.74631306824598,
      40.23737944303847,
      56.68603073855921,
      64.87402049124434,
      70.93296281243352,
      73.39975298519641,
      82.26650198945754,
      82.53664235152002,
      86.7048690051729,
      88.72112039913578,
      80.6163401527323,
      69.8260981132353,
      53.630378093064024,
      47.55299542466571,
      34.946834707831805,
      27.031223138494806,
      22.820815425586403,
      23.747210283587737,
      25.97640105844728,
      33.98426737189169,
      44.451050041961324,
      51.428905155341084,
      45.39704788087554,
      36.51469858698995,
      28.408173041534845,
      19.544842633728468,
      13.594866840545592,
      14.712962074296508,
      12.06852838843745,
      8.93457448115682,
      10.304209074268378,
      14.416642527214876,
      10.86895665331591,
      12.672327691105506,
      13.874575049631904,
      13.125685691822389,
      15.939999611259783,
      27.769523549384072,
      42.32253950775265,
      35.834073957114015,
      34.60366835159642,
      54.44166125216002,
      61.0070845120821
    ],
    "kd_d": [
      77.84125400669564,
      77.66064039696471,
      76.96597958615695,
      75.93788852471133,
      72.69313350858924,
      71.33727063959209,
      73.7173924243329,
      77.37805374152313,
      80.2685639109697,
      81.43681457602949,
      82.28701152020744,
      82.3241843507881,
      82.2844831049649,
      79.88740278578372,
      77.1847129065651,
      71.79340310489945,
      63.7594019122636,
      53.37535943529893,
      47.16567731294795,
      44.8562446896448,
      48.799506705949604,
      54.15767796771452,
      59.74943958262085,
      64.29954405014604,
      70.28853002991654,
      74.37123413711771,
      78.48244575980277,
      81.89533730624711,
      81.46900492174218,
      77.58803598557323,
      69.6021500214035,
      62.25243182249091,
      53.15056611760455,
      44.444118457901304,
      37.236350780463006,
      32.739970614837915,
      30.48544742937437,
      31.65172074354681,
      35.91816384301832,
      41.08841094712591,
      42.52462325837578,
      40.52131503458051,
      36.48360103689863,
      30.837348235841908,
      25.089854437409805,
      21.630890316372042,
      18.443436340393845,
      15.273815720648171,
      13.617280171854908,
      13.883734290308231,
      12.878808411310793,
      12.809981504575697,
      13.164846019594435,
      13.151792577003754,
      14.081194921755763,
      18.6439711309652,
      26.53682725656102,
      29.635909490078685,
      31.2918291105846,
      39.00843982444307,
      46.34132138698942
    ],
    "macd": [
      2.6575062890032086,
      3.755389344426959,
      4.373327472244142,
      4.767742501477045,
      4.583677438893375,
      5.025407917622516,
      6.27148840189605,
      8.173443329439209,
      9.690092422762888,
      10.488719576531992,
      11.154439203256715,
      11.389354133559436,
      11.523383162901382,
      10.978552537310009,
      10.745667545324608,
      10.44075004396484,
      9.803669380005317,
      8.7939489808347,
      8.50093215549208,
      8.373914048394681,
      9.056462094989087,
      9.32847025576828,
      9.8341351081649,
      10.038469279037827,
      12.1582357174251,
      14.039440354709399,
      15.991501647684743,
      17.936945661865536,
      17.980391021558603,
      17.131461989733452,
      15.074535118762356,
      13.929369791149497,
      11.716726075314398,
      9.490675003645151,
      7.798006215258738,
      6.941379600821961,
      6.310787471552999,
      5.984132242393002,
      5.380808262368589,
      4.846798782151495,
      3.65523239415063,
      2.400811635527134,
      1.5103017917563193,
      0.077448759836102,
      -1.2055836584471535,
      -1.8380952835015592,
      -2.5520221090171162,
      -3.8002323328937564,
      -4.615209205356763,
      -5.081470752667002,
      -5.787727284004973,
      -6.235219127258347,
      -6.514761521519432,
      -6.739306001108417,
      -6.91820203496178,
      -6.700320556813125,
      -6.174056486391095,
      -6.369444391486212,
      -6.4100537827546304,
      -5.451442294058893,
      -4.1995222696498615
    ],
    "macd_signal": [
      -0.7038763148855054,
      0.18797681697698754,
      1.0250469480304185,
      1.773586058719744,
      2.3356043347544704,
      2.8735650513280797,
      3.553149721441674,
      4.477208443041182,
      5.5197852389855235,
      6.513572106494818,
      7.441745525847198,
      8.231267247389646,
      8.889690430491994,
      9.307462851855597,
      9.595103790549398,
      9.764233041232487,
      9.772120308987054,
      9.576486043356583,
      9.361375265783682,
      9.163883022305882,
      9.142398836842522,
      9.179613120627675,
      9.310517518135121,
      9.456107870315662,
      9.99653343973755,
      10.805114822731921,
      11.842392187722487,
      13.061302882551098,
      14.0451205103526,
      14.66238880622877,
      14.744818068735489,
      14.581728413218292,
      14.008727945637514,
      13.105117357239042,
      12.043695128842982,
      11.02323202323878,
      10.080743112901624,
      9.2614209387999,
      8.485298403513639,
      7.75759847924121,
      6.937125262223094,
      6.029862536883902,
      5.125950387858387,
      4.11625006225393,
      3.0518833181137133,
      2.073887597790659,
      1.148705656429104,
      0.158918058564532,
      -0.795907394219727,
      -1.653020065909182,
      -2.4799615095283403,
      -3.2310130330743414,
      -3.8877627307633595,
      -4.458071384832372,
      -4.950097514858253,
      -5.300142123249228,
      -5.474924995877602,
      -5.653828874999324,
      -5.805073856550386,
      -5.734347544052088,
      -5.427382489171643
    ],
    "macd_hist": [
      3.361382603888714,
      3.5674125274499717,
      3.348280524213724,
      2.994156442757301,
      2.2480731041389044,
      2.1518428662944364,
      2.7183386804543765,
      3.6962348863980274,
      4.170307183777364,
      3.9751474700371734,
      3.7126936774095167,
      3.158086886169791,
      2.633692732409388,
      1.6710896854544117,
      1.1505637547752094,
      0.6765170027323535,
      0.03154907101826332,
      -0.7825370625218842,
      -0.8604431102916017,
      -0.7899689739112006,
      -0.0859367418534358,
      0.14885713514060583,
      0.5236175900297795,
      0.5823614087221642,
      2.1617022776875494,
      3.2343255319774773,
      4.149109459962256,
      4.875642779314438,
      3.935270511206003,
      2.4690731835046815,
      0.3297170500268667,
      -0.6523586220687942,
      -2.2920018703231158,
      -3.6144423535938905,
      -4.245688913584244,
      -4.081852422416819,
      -3.7699556413486253,
      -3.277288696406897,
      -3.1044901411450496,
      -2.9107996970897148,
      -3.2818928680724637,
      -3.629050901356768,
      -3.6156485961020675,
      -4.038801302417828,
      -4.257466976560867,
      -3.911982881292218,
      -3.7007277654462203,
      -3.959150391458288,
      -3.819301811137036,
      -3.42845068675782,
      -3.3077657744766324,
      -3.0042060941840054,
      -2.6269987907560726,
      -2.2812346162760457,
      -1.9681045201035268,
      -1.4001784335638972,
      -0.6991314905134924,
      -0.7156155164868876,
      -0.6049799262042441,
      0.28290524999319544,
      1.2278602195217818
    ],
    "rsi14": [
      61.54344117981711,
      66.02849665730847,
      62.98584860321956,
      62.36685122665886,
      55.86331055797842,
      62.06055953762344,
      69.07489213907733,
      74.38702480678094,
      74.94324712162069,
      71.06525292390532,
      71.95820289082798,
      69.64361629738158,
      70.1604374300246,
      62.689377375088334,
      65.14883083722646,
      65.14883083607023,
      61.06404666856149,
      55.6919755325162,
      61.20519953608004,
      62.86395486409408,
      69.120282534864,
      66.91300785062577,
      69.5324738283301,
      68.36669876065703,
      78.47262602549588,
      79.68246222739485,
      81.65618986971677,
      83.29462185699995,
      69.11256327180642,
      62.97785641524567,
      53.88748288406446,
      57.41773726877214,
      49.95304606971929,
      47.872941900928105,
      48.89157497007844,
      52.39775881313485,
      53.13962545588741,
      54.66150480589299,
      52.51852318046731,
      52.51852317983377,
      47.020937807890704,
      45.046119782261755,
      46.09109078261141,
      41.04761708958387,
      40.00013548268704,
      43.494107295740584,
      41.748666354757084,
      36.957089712008056,
      38.229566631029385,
      39.54370137556361,
      36.738019547290705,
      37.21773396491996,
      37.217733964312096,
      36.57442899599736,
      35.90605528892905,
      40.03636378200231,
      43.92769821255886,
      37.55386366165735,
      38.12262488896759,
      49.51253923941822,
      53.884580685828496
    ]
  },
  "chip": {
    "dates": [
      "2026-07-15",
      "2026-07-16",
      "2026-07-17",
      "2026-07-20",
      "2026-07-21",
      "2026-07-22"
    ],
    "foreign": [
      6880,
      6698,
      -4269,
      60,
      22635,
      17679
    ],
    "trust": [
      -890,
      -1057,
      -696,
      449,
      2099,
      665
    ],
    "dealer": [
      401,
      1344,
      2133,
      3411,
      2230,
      -179
    ],
    "total": [
      6391,
      6985,
      -2832,
      3920,
      26964,
      18165
    ]
  },
  "signal": {
    "label": "吸籌期",
    "color": "#27ae60",
    "desc": "主力持續買超，籌碼集中"
  },
  "summary": [
    {
      "label": "趨勢方向",
      "value": "空頭趨勢",
      "direction": "down"
    },
    {
      "label": "價格位置",
      "value": "中軌以上",
      "direction": "up"
    },
    {
      "label": "均線排列",
      "value": "空頭排列（5<20<60）",
      "direction": "down"
    },
    {
      "label": "量價關係",
      "value": "量能平穩",
      "direction": "neutral"
    },
    {
      "label": "布林位置",
      "value": "中軌區間（80%）",
      "direction": "neutral"
    },
    {
      "label": "布林通道",
      "value": "開口收斂（蓄勢待發）",
      "direction": "neutral"
    },
    {
      "label": "KD狀態",
      "value": "K 61.0 / D 46.3",
      "direction": "neutral"
    },
    {
      "label": "綜合評估",
      "value": "盤整觀望",
      "direction": "neutral"
    }
  ],
  "levels": {
    "resistance": "260 ～ 260",
    "pullback": "237 ～ 249",
    "support": "200 ～ 200",
    "breakdown": 243.0,
    "breakout": 309.0
  },
  "patterns": [
    {
      "label": "W底（未完成）",
      "desc": "右肩未完成，且頸線未突破",
      "date": ""
    },
    {
      "label": "M頭（未完成）",
      "desc": "右峰已形成，尚未跌破頸線",
      "date": ""
    }
  ],
  "prediction": {
    "up": 0.33,
    "sideways": 0.34,
    "down": 0.33,
    "accuracy": 0.0,
    "error": "model not trained — run python model/train.py first"
  }
}