{
  "stock_id": "2609",
  "name": "2609",
  "industry": "—",
  "generated_at": "2026-07-21 10:38",
  "quote": {
    "close": 50.9,
    "prev": 49.0,
    "change": 1.9,
    "change_pct": 3.88,
    "volume": 27795467
  },
  "ohlcv": {
    "date": [
      "2026-04-23",
      "2026-04-24",
      "2026-04-27",
      "2026-04-28",
      "2026-04-29",
      "2026-04-30",
      "2026-05-04",
      "2026-05-05",
      "2026-05-06",
      "2026-05-07",
      "2026-05-08",
      "2026-05-11",
      "2026-05-12",
      "2026-05-13",
      "2026-05-14",
      "2026-05-15",
      "2026-05-18",
      "2026-05-19",
      "2026-05-20",
      "2026-05-21",
      "2026-05-22",
      "2026-05-25",
      "2026-05-26",
      "2026-05-27",
      "2026-05-28",
      "2026-05-29",
      "2026-06-01",
      "2026-06-02",
      "2026-06-03",
      "2026-06-04",
      "2026-06-05",
      "2026-06-08",
      "2026-06-09",
      "2026-06-10",
      "2026-06-11",
      "2026-06-12",
      "2026-06-15",
      "2026-06-16",
      "2026-06-17",
      "2026-06-18",
      "2026-06-22",
      "2026-06-23",
      "2026-06-24",
      "2026-06-25",
      "2026-06-26",
      "2026-06-29",
      "2026-06-30",
      "2026-07-01",
      "2026-07-02",
      "2026-07-03",
      "2026-07-06",
      "2026-07-07",
      "2026-07-08",
      "2026-07-09",
      "2026-07-13",
      "2026-07-14",
      "2026-07-15",
      "2026-07-16",
      "2026-07-17",
      "2026-07-20",
      "2026-07-21"
    ],
    "open": [
      51.4,
      50.3,
      50.0,
      49.35,
      49.5,
      49.4,
      49.2,
      49.85,
      50.4,
      50.9,
      50.7,
      50.3,
      51.0,
      50.1,
      49.15,
      48.9,
      47.7,
      49.0,
      49.95,
      50.3,
      51.9,
      53.0,
      51.8,
      51.7,
      52.9,
      53.0,
      53.6,
      55.0,
      53.9,
      54.1,
      53.8,
      52.0,
      52.1,
      51.9,
      51.0,
      51.8,
      53.7,
      51.2,
      51.1,
      51.6,
      52.0,
      52.7,
      51.4,
      51.6,
      51.4,
      50.8,
      51.9,
      52.1,
      51.2,
      51.2,
      53.0,
      52.1,
      51.2,
      52.5,
      51.4,
      49.0,
      48.1,
      49.9,
      49.5,
      49.9,
      49.8
    ],
    "high": [
      51.9,
      50.5,
      50.1,
      50.4,
      49.95,
      49.7,
      50.4,
      50.9,
      50.6,
      51.0,
      50.7,
      50.9,
      51.0,
      50.1,
      49.2,
      48.9,
      49.3,
      50.5,
      50.8,
      51.1,
      53.9,
      53.1,
      53.0,
      53.8,
      53.5,
      53.3,
      55.7,
      55.0,
      55.3,
      54.4,
      55.2,
      52.6,
      52.6,
      52.1,
      51.3,
      53.3,
      53.7,
      51.7,
      52.1,
      52.5,
      52.7,
      52.8,
      52.1,
      52.0,
      51.4,
      51.7,
      52.2,
      52.1,
      51.3,
      53.6,
      53.6,
      52.2,
      52.3,
      52.5,
      51.4,
      49.4,
      50.2,
      50.6,
      50.3,
      50.7,
      51.3
    ],
    "low": [
      49.95,
      49.9,
      49.1,
      49.05,
      49.2,
      49.1,
      49.2,
      49.35,
      49.8,
      50.3,
      49.8,
      50.1,
      50.0,
      49.2,
      48.3,
      48.0,
      47.35,
      48.25,
      49.45,
      49.95,
      51.8,
      51.0,
      51.6,
      51.2,
      52.0,
      52.4,
      53.6,
      52.9,
      52.9,
      52.7,
      53.3,
      51.1,
      51.1,
      50.5,
      50.0,
      51.4,
      51.2,
      50.2,
      50.3,
      51.3,
      51.4,
      51.2,
      51.2,
      51.2,
      50.1,
      50.4,
      51.5,
      50.6,
      50.5,
      51.2,
      52.6,
      51.1,
      51.2,
      51.5,
      50.1,
      47.25,
      48.1,
      49.8,
      49.2,
      48.95,
      49.7
    ],
    "close": [
      50.1,
      50.1,
      49.35,
      49.5,
      49.35,
      49.15,
      49.95,
      50.1,
      50.6,
      50.7,
      49.9,
      50.8,
      50.1,
      49.25,
      48.6,
      48.05,
      48.55,
      49.5,
      50.3,
      51.1,
      53.0,
      51.8,
      52.0,
      52.6,
      52.3,
      52.7,
      54.9,
      53.6,
      53.7,
      53.2,
      54.5,
      51.7,
      51.6,
      50.6,
      51.1,
      52.4,
      51.2,
      51.0,
      51.6,
      51.3,
      52.3,
      51.3,
      51.6,
      51.4,
      50.1,
      51.4,
      52.0,
      50.7,
      51.0,
      52.4,
      53.0,
      51.1,
      52.3,
      51.6,
      50.1,
      48.0,
      50.2,
      50.2,
      49.2,
      49.0,
      50.9
    ],
    "volume": [
      30282709,
      16405527,
      20113302,
      14634767,
      10895125,
      11508316,
      18782956,
      15055914,
      18046009,
      15114698,
      17222047,
      17725847,
      10783318,
      17974943,
      22899538,
      19214667,
      13803497,
      19201610,
      23983815,
      19862642,
      44488347,
      29869029,
      14910096,
      32824282,
      16197736,
      29776823,
      51690436,
      71874958,
      61465906,
      54851079,
      78583004,
      66798155,
      61977162,
      56863530,
      52461697,
      30718280,
      39646266,
      32633400,
      34556058,
      34519700,
      38001527,
      19953550,
      15479059,
      11437515,
      24041295,
      17994950,
      13913659,
      16922998,
      10558613,
      43386845,
      19345058,
      22349000,
      14771426,
      11769457,
      34126647,
      34992080,
      20165444,
      10433684,
      16323681,
      17602639,
      27795467
    ]
  },
  "indicators": {
    "ma5": [
      50.42,
      50.3,
      50.15,
      49.910000000000004,
      49.68,
      49.49,
      49.46,
      49.61,
      49.83,
      50.1,
      50.25,
      50.42,
      50.42,
      50.15,
      49.730000000000004,
      49.36,
      48.91,
      48.79,
      49.0,
      49.5,
      50.489999999999995,
      51.14,
      51.64,
      52.1,
      52.339999999999996,
      52.279999999999994,
      52.9,
      53.220000000000006,
      53.44,
      53.620000000000005,
      53.980000000000004,
      53.34000000000001,
      52.94,
      52.32000000000001,
      51.9,
      51.480000000000004,
      51.379999999999995,
      51.260000000000005,
      51.46,
      51.5,
      51.480000000000004,
      51.5,
      51.620000000000005,
      51.58,
      51.339999999999996,
      51.160000000000004,
      51.3,
      51.12,
      51.04,
      51.5,
      51.82000000000001,
      51.64,
      51.96,
      52.08,
      51.620000000000005,
      50.62,
      50.440000000000005,
      50.019999999999996,
      49.540000000000006,
      49.32000000000001,
      49.9
    ],
    "ma20": [
      51.504999999999995,
      51.325,
      51.1625,
      51.0175,
      50.835,
      50.6925,
      50.555,
      50.455,
      50.4,
      50.35,
      50.28,
      50.255,
      50.23,
      50.1725,
      50.027499999999996,
      49.88,
      49.7725,
      49.7425,
      49.7225,
      49.7525,
      49.897499999999994,
      49.9825,
      50.115,
      50.269999999999996,
      50.417500000000004,
      50.595,
      50.8425,
      51.0175,
      51.1725,
      51.2975,
      51.527499999999996,
      51.572500000000005,
      51.6475,
      51.714999999999996,
      51.839999999999996,
      52.05749999999999,
      52.19,
      52.265,
      52.330000000000005,
      52.339999999999996,
      52.30500000000001,
      52.279999999999994,
      52.260000000000005,
      52.2,
      52.089999999999996,
      52.025,
      51.879999999999995,
      51.735,
      51.6,
      51.56,
      51.485,
      51.455000000000005,
      51.489999999999995,
      51.54,
      51.489999999999995,
      51.27,
      51.21999999999999,
      51.17999999999999,
      51.06,
      50.945,
      50.875
    ],
    "ma60": [
      54.72833333333333,
      54.655,
      54.5775,
      54.48416666666667,
      54.38666666666666,
      54.280833333333334,
      54.208333333333336,
      54.13833333333333,
      54.083333333333336,
      54.015,
      53.934999999999995,
      53.891666666666666,
      53.855000000000004,
      53.8025,
      53.7325,
      53.65333333333333,
      53.5925,
      53.5475,
      53.50583333333334,
      53.469166666666666,
      53.4275,
      53.35916666666666,
      53.2875,
      53.2075,
      53.079166666666666,
      52.8575,
      52.7125,
      52.60583333333334,
      52.48916666666666,
      52.34916666666666,
      52.2575,
      52.104166666666664,
      51.92916666666667,
      51.785833333333336,
      51.649166666666666,
      51.5475,
      51.42916666666667,
      51.3375,
      51.2625,
      51.2375,
      51.23583333333333,
      51.19583333333333,
      51.17916666666667,
      51.1625,
      51.11416666666666,
      51.104166666666664,
      51.0925,
      51.06916666666667,
      51.0575,
      51.06916666666667,
      51.0975,
      51.094166666666666,
      51.12250000000001,
      51.142500000000005,
      51.119166666666665,
      51.06916666666667,
      51.06083333333333,
      51.0625,
      51.0375,
      51.0125,
      51.02583333333334
    ],
    "bb_upper": [
      53.546129718150105,
      53.177310079759515,
      53.11155510170272,
      53.00992644980798,
      52.72906274558426,
      52.645439754372916,
      52.287628061644966,
      52.03643838590715,
      51.87184095250581,
      51.69868356867747,
      51.56489196760684,
      51.474102344479455,
      51.439784669835056,
      51.4553730092625,
      51.33395160242281,
      51.37645194411717,
      51.328633873282875,
      51.295180195492,
      51.23298092724745,
      51.34936370245238,
      52.05534370928101,
      52.30181818474843,
      52.58036001427774,
      52.95277154411147,
      53.209457434451515,
      53.49688686347705,
      54.30329926880295,
      54.668927262404566,
      55.00785835147256,
      55.229751932818864,
      55.64913419301767,
      55.680319885356006,
      55.69647322916887,
      55.63876028024674,
      55.496083610698875,
      55.25277200061194,
      54.965001185395664,
      54.80501657682117,
      54.720419474309466,
      54.710343079764925,
      54.65489361461323,
      54.662921691846726,
      54.65947362648781,
      54.623568486865246,
      54.687893883817985,
      54.623683877415026,
      54.09915109421311,
      53.857833260675804,
      53.5314570447694,
      53.38197117083896,
      52.86801729638682,
      52.8443959308388,
      52.929151796975106,
      52.91710604262396,
      53.00052448193538,
      53.3837146150046,
      53.38731704138885,
      53.39345169837799,
      53.432118750910426,
      53.48518233908301,
      53.33381871509145
    ],
    "bb_lower": [
      49.463870281849886,
      49.47268992024049,
      49.21344489829728,
      49.02507355019202,
      48.94093725441574,
      48.73956024562709,
      48.82237193835503,
      48.87356161409285,
      48.928159047494184,
      49.001316431322536,
      48.99510803239316,
      49.03589765552055,
      49.02021533016494,
      48.8896269907375,
      48.721048397577185,
      48.383548055882834,
      48.216366126717126,
      48.189819804508,
      48.21201907275254,
      48.155636297547616,
      47.739656290718976,
      47.663181815251576,
      47.64963998572227,
      47.58722845588852,
      47.62554256554849,
      47.693113136522946,
      47.38170073119705,
      47.36607273759543,
      47.33714164852744,
      47.365248067181135,
      47.40586580698232,
      47.464680114644004,
      47.59852677083113,
      47.79123971975325,
      48.18391638930112,
      48.86222799938804,
      49.41499881460433,
      49.724983423178834,
      49.939580525690545,
      49.96965692023507,
      49.955106385386784,
      49.89707830815326,
      49.8605263735122,
      49.77643151313476,
      49.49210611618201,
      49.42631612258497,
      49.66084890578688,
      49.612166739324195,
      49.668542955230606,
      49.738028829161046,
      50.10198270361318,
      50.06560406916121,
      50.050848203024884,
      50.162893957376035,
      49.97947551806461,
      49.15628538499541,
      49.052682958611136,
      48.966548301622,
      48.68788124908958,
      48.40481766091699,
      48.41618128490855
    ],
    "bb_mid": [
      51.504999999999995,
      51.325,
      51.1625,
      51.0175,
      50.835,
      50.6925,
      50.555,
      50.455,
      50.4,
      50.35,
      50.28,
      50.255,
      50.23,
      50.1725,
      50.027499999999996,
      49.88,
      49.7725,
      49.7425,
      49.7225,
      49.7525,
      49.897499999999994,
      49.9825,
      50.115,
      50.269999999999996,
      50.417500000000004,
      50.595,
      50.8425,
      51.0175,
      51.1725,
      51.2975,
      51.527499999999996,
      51.572500000000005,
      51.6475,
      51.714999999999996,
      51.839999999999996,
      52.05749999999999,
      52.19,
      52.265,
      52.330000000000005,
      52.339999999999996,
      52.30500000000001,
      52.279999999999994,
      52.260000000000005,
      52.2,
      52.089999999999996,
      52.025,
      51.879999999999995,
      51.735,
      51.6,
      51.56,
      51.485,
      51.455000000000005,
      51.489999999999995,
      51.54,
      51.489999999999995,
      51.27,
      51.21999999999999,
      51.17999999999999,
      51.06,
      50.945,
      50.875
    ],
    "kd_k": [
      17.3395745115921,
      14.893049672728115,
      12.904890256946299,
      13.866418064187684,
      12.753050638051919,
      9.671624401565767,
      16.974065386824144,
      23.596745341293087,
      33.859818525261396,
      50.77834054083836,
      48.38214154968887,
      62.16929093231499,
      58.99005359476588,
      41.95828134249395,
      31.675891263994647,
      21.67281639803344,
      25.407448371942195,
      36.57300210559578,
      51.322640665755884,
      67.54842710161503,
      73.78546539159784,
      71.83662069017774,
      71.55520259391024,
      74.42102564376955,
      74.80485678665693,
      76.12359183542553,
      79.81572788563301,
      74.36990554326384,
      68.7288731949811,
      61.422085672766954,
      65.39250155419029,
      47.94282712213822,
      35.5850731531016,
      24.36440774297011,
      22.675687032196556,
      30.211464307924558,
      27.688146015179825,
      24.869020419143553,
      26.83575720053358,
      29.60221650890207,
      40.4555317210552,
      38.682066189249824,
      40.20245853668518,
      38.23021044976287,
      25.486806966508585,
      33.04058735444421,
      45.483848351065255,
      37.72997297204079,
      36.26442642168975,
      46.08104617962988,
      58.33974506424303,
      48.41697289725046,
      53.230362877894834,
      47.986908581357,
      31.991272387571335,
      25.264522798443306,
      32.328579500985484,
      37.037950636013605,
      34.92818756150469,
      34.39656948333117,
      46.10564949240974
    ],
    "kd_d": [
      18.828579521853406,
      17.516736238811646,
      15.97945424485653,
      15.27510885130025,
      14.434422780217474,
      12.846823320666907,
      14.222570676052655,
      17.347295564466133,
      22.851469884731223,
      32.160426770100266,
      37.56766502996314,
      45.768206997413756,
      50.17548919653113,
      47.43641991185207,
      42.18291036256627,
      35.346212374388664,
      32.033291040239845,
      33.54652806202516,
      39.471898929935406,
      48.83074165382862,
      57.148982899751694,
      62.044862163227045,
      65.21497564012145,
      68.28365897467083,
      70.4573915786662,
      72.34612499758597,
      74.835992626935,
      74.68063026571129,
      72.69671124213457,
      68.93850271901204,
      67.75650233073813,
      61.1519439278715,
      52.62965366961487,
      43.207905027399946,
      36.363832362332154,
      34.313043010862955,
      32.104744012301914,
      29.6928361479158,
      28.740476498788396,
      29.02772316882629,
      32.83699268623593,
      34.7853505205739,
      36.59105319261099,
      37.137438944994955,
      33.25389495216616,
      33.18279241959218,
      37.283144396749876,
      37.432087255180186,
      37.042866977350045,
      40.05559337810999,
      46.15031060682101,
      46.905864703630826,
      49.01403076171883,
      48.67165670159822,
      43.1115285969226,
      37.16252666409617,
      35.551210943059274,
      36.04679084071072,
      35.67392308097538,
      35.248138548427306,
      38.86730886308812
    ],
    "macd": [
      -1.4022625369340176,
      -1.3714761140134968,
      -1.3915553995998309,
      -1.3794630404483854,
      -1.3662344053246258,
      -1.3562548831584351,
      -1.2691626092885357,
      -1.1744987182589597,
      -1.0470612114037792,
      -0.9273074814015345,
      -0.8867333911558859,
      -0.7730444783861472,
      -0.7310028005365083,
      -0.757539915605463,
      -0.8215500209659794,
      -0.9062126388869984,
      -0.9223305003477762,
      -0.8486640898073858,
      -0.7174591916369195,
      -0.5426694943052084,
      -0.24797477993643469,
      -0.10998918001860147,
      0.015327049888739452,
      0.16119786192567176,
      0.24971547406942562,
      0.3481299511157303,
      0.5967665932333048,
      0.6810629186162203,
      0.7473228553849793,
      0.7508333715954265,
      0.8487309740783147,
      0.6923974036694318,
      0.5540460604297692,
      0.3595651383994962,
      0.24298247711197263,
      0.25257745784553975,
      0.16149002157872872,
      0.07233046300411416,
      0.04951507707808389,
      0.007143876400107274,
      0.05363773482733336,
      0.00968121097599095,
      -0.0009363642463000588,
      -0.0251987224489838,
      -0.14762423132631142,
      -0.13815562168517914,
      -0.08129952442577348,
      -0.1395313624769372,
      -0.15963287248879965,
      -0.06188182907941098,
      0.06327220013397294,
      0.009039348946359382,
      0.06217270657490559,
      0.047252428858520545,
      -0.08463385629088549,
      -0.354520446008614,
      -0.3864313587959032,
      -0.40702901002473624,
      -0.4983003434943427,
      -0.5800850025546325,
      -0.48598369552149023
    ],
    "macd_signal": [
      -1.4434222367135618,
      -1.4290330121735488,
      -1.4215374896588053,
      -1.4131225998167214,
      -1.4037449609183024,
      -1.394246945366329,
      -1.3692300781507705,
      -1.3302838061724083,
      -1.2736392872186826,
      -1.2043729260552531,
      -1.1408450190753798,
      -1.0672849109375333,
      -1.0000284888573283,
      -0.9515307742069553,
      -0.9255346235587601,
      -0.9216702266244079,
      -0.9218022813690816,
      -0.9071746430567426,
      -0.869231552772778,
      -0.8039191410792641,
      -0.6927302688506982,
      -0.5761820510842789,
      -0.4578802308896752,
      -0.33406461232660584,
      -0.21730859504739955,
      -0.10422088581477358,
      0.035976609994842104,
      0.16499387171911772,
      0.2814596684522901,
      0.3753344090809174,
      0.4700137220803969,
      0.5144904583982038,
      0.5224015788045169,
      0.4898342907235128,
      0.4404639280012048,
      0.40288663397007185,
      0.35460731149180325,
      0.2981519417942654,
      0.24842456885102912,
      0.20016843036084475,
      0.17086229125414248,
      0.1386260751985122,
      0.11071358730954975,
      0.08353112535784304,
      0.037300054021012156,
      0.0022089188797738968,
      -0.01449276978133558,
      -0.039500488320455905,
      -0.06352696515412465,
      -0.06319793793918191,
      -0.03790391032455094,
      -0.028515258470368877,
      -0.010377665461313985,
      0.0011483534026529227,
      -0.01600808853605476,
      -0.08371056003056661,
      -0.1442547197836339,
      -0.19680957783185438,
      -0.2571077309643521,
      -0.32170318528240816,
      -0.35455928733022457
    ],
    "macd_hist": [
      0.041159699779544257,
      0.05755689816005205,
      0.029982090058974453,
      0.03365955936833598,
      0.03751055559367655,
      0.03799206220789397,
      0.10006746886223472,
      0.15578508791344858,
      0.2265780758149034,
      0.27706544465371863,
      0.25411162791949393,
      0.2942404325513861,
      0.26902568832081997,
      0.19399085860149234,
      0.10398460259278075,
      0.015457587737409462,
      -0.0005282189786945946,
      0.05851055324935672,
      0.15177236113585846,
      0.2612496467740557,
      0.44475548891426353,
      0.4661928710656774,
      0.4732072807784147,
      0.4952624742522776,
      0.46702406911682515,
      0.4523508369305039,
      0.5607899832384627,
      0.5160690468971025,
      0.46586318693268924,
      0.3754989625145091,
      0.3787172519979178,
      0.17790694527122797,
      0.03164448162525235,
      -0.1302691523240166,
      -0.1974814508892322,
      -0.1503091761245321,
      -0.19311728991307453,
      -0.22582147879015124,
      -0.19890949177294523,
      -0.19302455396073748,
      -0.11722455642680912,
      -0.12894486422252124,
      -0.11164995155584981,
      -0.10872984780682685,
      -0.18492428534732358,
      -0.14036454056495304,
      -0.0668067546444379,
      -0.10003087415648129,
      -0.096105907334675,
      0.0013161088597709314,
      0.10117611045852389,
      0.03755460741672826,
      0.07255037203621957,
      0.04610407545586762,
      -0.06862576775483073,
      -0.2708098859780474,
      -0.24217663901226927,
      -0.21021943219288186,
      -0.24119261252999064,
      -0.2583818172722243,
      -0.13142440819126566
    ],
    "rsi14": [
      35.79972150984629,
      35.7997215057477,
      32.76952004577974,
      33.97324288121422,
      33.330573278448256,
      32.44916386428913,
      39.35726023409537,
      40.58417873860332,
      44.607211426550606,
      45.403428532631644,
      40.40034224133236,
      47.41987440977226,
      43.16188103810692,
      38.62629692675444,
      35.549847903197644,
      33.14432320513788,
      37.29811449088431,
      44.37026734113073,
      49.5324603197614,
      54.11765281508001,
      62.76923757900489,
      55.63408420548614,
      56.521174230423185,
      59.159424768283834,
      57.2876485910314,
      59.14379166602278,
      67.50734057340406,
      59.72684165191499,
      60.10772030000516,
      57.19509627399967,
      62.3089721408718,
      48.78894782863696,
      48.38514847471951,
      44.42546200289287,
      46.77104781186323,
      52.39667310650209,
      47.415145411188924,
      46.619607493776115,
      49.364377060494114,
      48.03443862861709,
      52.616957341669114,
      48.05345836947365,
      49.46935961804633,
      48.519871798525315,
      42.773124231596036,
      49.24679529800236,
      51.94857211259573,
      46.20888432184571,
      47.64643608024506,
      53.84540360230529,
      56.237001056268326,
      47.79174126302669,
      52.63017673118232,
      49.73465812755348,
      44.131668933907,
      37.724113026020675,
      46.48946595238935,
      46.48946594918628,
      43.27827511754611,
      42.64384672253269,
      50.12403106887153
    ]
  },
  "chip": {
    "dates": [
      "2026-07-14",
      "2026-07-15",
      "2026-07-16",
      "2026-07-17",
      "2026-07-20",
      "2026-07-21"
    ],
    "foreign": [
      -7510,
      11205,
      2849,
      4729,
      -584,
      12481
    ],
    "trust": [
      182,
      -44,
      15,
      -59,
      -175,
      -1
    ],
    "dealer": [
      -349,
      142,
      -77,
      -119,
      14,
      228
    ],
    "total": [
      -7677,
      11303,
      2787,
      4551,
      -745,
      12708
    ]
  },
  "signal": {
    "label": "吸籌期",
    "color": "#27ae60",
    "desc": "主力持續買超，籌碼集中"
  },
  "summary": [
    {
      "label": "趨勢方向",
      "value": "空頭趨勢",
      "direction": "down"
    },
    {
      "label": "價格位置",
      "value": "中軌以上",
      "direction": "up"
    },
    {
      "label": "均線排列",
      "value": "空頭排列（5<20<60）",
      "direction": "down"
    },
    {
      "label": "量價關係",
      "value": "量能平穩",
      "direction": "neutral"
    },
    {
      "label": "布林位置",
      "value": "中軌區間（51%）",
      "direction": "neutral"
    },
    {
      "label": "布林通道",
      "value": "開口擴大（趨勢加速）",
      "direction": "up"
    },
    {
      "label": "KD狀態",
      "value": "黃金交叉",
      "direction": "up"
    },
    {
      "label": "綜合評估",
      "value": "盤整觀望",
      "direction": "neutral"
    }
  ],
  "levels": {
    "resistance": "50 ～ 50",
    "pullback": "50 ～ 52",
    "support": "0 ～ 0",
    "breakdown": 51.0,
    "breakout": 55.0
  },
  "patterns": [
    {
      "label": "W底（未完成）",
      "desc": "右肩未完成，且頸線未突破",
      "date": ""
    },
    {
      "label": "M頭（未完成）",
      "desc": "右峰已形成，尚未跌破頸線",
      "date": ""
    }
  ],
  "prediction": {
    "up": 0.33,
    "sideways": 0.34,
    "down": 0.33,
    "accuracy": 0.0,
    "error": "model not trained — run python model/train.py first"
  }
}